{
	"images": [
        {
            "title": "",
            "description": "",
            "url": "setting_01.jpg"
        },
        {
            "title": "",
            "description": "",
            "url": "setting_02.jpg"
        },
        {
            "title": "",
            "description": "",
            "url": "setting_03.jpg"
        },
        {
            "title": "",
            "description": "",
            "url": "setting_04.jpg"
        },
        {
            "title": "",
            "description": "",
            "url": "setting_05.jpg"
        },
        {
            "title": "",
            "description": "",
            "url": "setting_06.jpg"
        },
        {
            "title": "",
            "description": "",
            "url": "setting_07.jpg"
        },
        {
            "title": "",
            "description": "",
            "url": "setting_08.jpg"
        },
        {
            "title": "",
            "description": "",
            "url": "setting_09.jpg"
        },
        {
            "title": "",
            "description": "",
            "url": "setting_10.jpg"
        },
        {
            "title": "",
            "description": "",
            "url": "setting_11.jpg"
        },
        {
            "title": "",
            "description": "",
            "url": "setting_12.jpg"
        },
        {
            "title": "",
            "description": "",
            "url": "setting_13.jpg"
        },
        {
            "title": "",
            "description": "",
            "url": "setting_14.jpg"
        },
        {
            "title": "",
            "description": "",
            "url": "setting_15.jpg"
        },
        {
            "title": "",
            "description": "",
            "url": "setting_16.jpg"
        },
        {
            "title": "",
            "description": "",
            "url": "setting_17.jpg"
        },
        {
            "title": "",
            "description": "",
            "url": "setting_18.jpg"
        },
        {
            "title": "",
            "description": "",
            "url": "setting_19.jpg"
        },
        {
            "title": "",
            "description": "",
            "url": "setting_20.jpg"
        },
        {
            "title": "",
            "description": "",
            "url": "setting_21.jpg"
        },
        {
            "title": "",
            "description": "",
            "url": "setting_22.jpg"
        },
        {
            "title": "",
            "description": "",
            "url": "setting_23.jpg"
        },
        {
            "title": "",
            "description": "",
            "url": "setting_24.jpg"
        },
        {
            "title": "",
            "description": "",
            "url": "setting_25.jpg"
        }
    ]
}